octopus_parser/infant_milk/__init__.py
octopus_parser/infant_milk/parser.py
octopus_parser/infant_milk/test_parser.py
octopus_parser-0.1.0.dist-info/METADATA
octopus_parser-0.1.0.dist-info/WHEEL
octopus_parser-0.1.0.dist-info/top_level.txt
octopus_parser-0.1.0.dist-info/RECORD
