Metadata-Version: 2.1
Name: octopus-parser
Version: 0.1.0
Summary: This package contains utility parsers
Home-page: https://octopusai.com
Author: OctopusAI, Inc
Author-email: hi@octopusai.com
License: Apache License, Version 2.0
Keywords: octopus parser
Platform: UNKNOWN
Classifier: Development Status :: 3 - Alpha
Classifier: Intended Audience :: Developers
Classifier: Natural Language :: English
Classifier: Operating System :: POSIX :: Linux
Classifier: Programming Language :: Python :: 3.6
Classifier: License :: OSI Approved :: Apache Software License
Requires-Dist: click (>=7.0)
Requires-Dist: lark-parser (>=0.7.8)
